{"v":"5.5.9","fr":24,"ip":0,"op":49,"w":500,"h":500,"nm":"105-\u001floader-1","ddd":0,"assets":[],"layers":[{"ddd":0,"ind":1,"ty":3,"nm":"Color  & Stroke Change","sr":1,"ks":{"o":{"a":0,"k":0,"ix":11},"r":{"a":0,"k":0,"ix":10},"p":{"a":0,"k":[0,0],"ix":2},"a":{"a":0,"k":[0,0,0],"ix":1},"s":{"a":0,"k":[100,100,100],"ix":6}},"ao":0,"ef":[{"ty":5,"nm":"Color 1 ","np":3,"mn":"ADBE Color Control","ix":1,"en":1,"ef":[{"ty":2,"nm":"Color","mn":"ADBE Color Control-0001","ix":1,"v":{"a":0,"k":[0.070588238537,0.074509806931,0.192156866193,1],"ix":1}}]},{"ty":5,"nm":"Color 2","np":3,"mn":"ADBE Color Control","ix":2,"en":1,"ef":[{"ty":2,"nm":"Color","mn":"ADBE Color Control-0001","ix":1,"v":{"a":0,"k":[0.031372550875,0.658823549747,0.541176497936,1],"ix":1}}]},{"ty":5,"nm":"Slider Control","np":3,"mn":"ADBE Slider Control","ix":3,"en":1,"ef":[{"ty":0,"nm":"Slider","mn":"ADBE Slider Control-0001","ix":1,"v":{"a":0,"k":100,"ix":1}}]}],"ip":0,"op":120,"st":0,"bm":0},{"ddd":0,"ind":2,"ty":3,"nm":"NULL","sr":1,"ks":{"o":{"a":0,"k":0,"ix":11},"r":{"a":0,"k":0,"ix":10},"p":{"a":0,"k":[250,250,0],"ix":2},"a":{"a":0,"k":[60,60,0],"ix":1},"s":{"a":0,"k":[620,620,100],"ix":6}},"ao":0,"ip":0,"op":120,"st":0,"bm":0},{"ddd":0,"ind":3,"ty":4,"nm":"Shape Layer 4","parent":2,"sr":1,"ks":{"o":{"a":0,"k":100,"ix":11},"r":{"a":0,"k":0,"ix":10},"p":{"a":1,"k":[{"i":{"x":0.833,"y":0.833},"o":{"x":0.167,"y":0.167},"t":12,"s":[116.5,60,0],"to":[-9.417,0,0],"ti":[9.417,0,0]},{"i":{"x":0.833,"y":0.833},"o":{"x":0.167,"y":0.167},"t":36,"s":[60,60,0],"to":[0,0,0],"ti":[0,0,0]},{"t":48,"s":[60,60,0]}],"ix":2},"a":{"a":0,"k":[0,0,0],"ix":1},"s":{"a":0,"k":[100,-100,100],"ix":6}},"ao":0,"shapes":[{"ty":"gr","it":[{"d":1,"ty":"el","s":{"a":0,"k":[57,57],"ix":2},"p":{"a":0,"k":[0,0],"ix":3},"nm":"Ellipse Path 1","mn":"ADBE Vector Shape - Ellipse","hd":false},{"ty":"tm","s":{"a":1,"k":[{"i":{"x":[0],"y":[1]},"o":{"x":[0.167],"y":[0.167]},"t":36,"s":[49.9]},{"t":48,"s":[0]}],"ix":1},"e":{"a":1,"k":[{"i":{"x":[0.667],"y":[1]},"o":{"x":[0.167],"y":[0.167]},"t":36,"s":[50]},{"t":48,"s":[0.1]}],"ix":2},"o":{"a":0,"k":90,"ix":3},"m":1,"ix":2,"nm":"Trim Paths 1","mn":"ADBE Vector Filter - Trim","hd":false},{"ty":"st","c":{"a":0,"k":[0.070588235294,0.074509803922,0.192156862745,1],"ix":3,"x":"var $bm_rt;\n$bm_rt = thisComp.layer('Color  & Stroke Change').effect('Color 1 ')('Color');"},"o":{"a":0,"k":100,"ix":4},"w":{"a":0,"k":10,"ix":5},"lc":2,"lj":2,"bm":0,"nm":"Stroke 1","mn":"ADBE Vector Graphic - Stroke","hd":false},{"ty":"tr","p":{"a":0,"k":[0,0],"ix":2},"a":{"a":0,"k":[0,0],"ix":1},"s":{"a":0,"k":[100,100],"ix":3},"r":{"a":0,"k":0,"ix":6},"o":{"a":0,"k":100,"ix":7},"sk":{"a":0,"k":0,"ix":4},"sa":{"a":0,"k":0,"ix":5},"nm":"Transform"}],"nm":"Ellipse 1","np":3,"cix":2,"bm":0,"ix":1,"mn":"ADBE Vector Group","hd":false}],"ip":36,"op":49,"st":12,"bm":0},{"ddd":0,"ind":4,"ty":4,"nm":"Shape Layer 2","parent":2,"sr":1,"ks":{"o":{"a":0,"k":100,"ix":11},"r":{"a":0,"k":0,"ix":10},"p":{"a":1,"k":[{"i":{"x":0.833,"y":0.833},"o":{"x":0.167,"y":0.167},"t":0,"s":[116.5,60,0],"to":[-9.417,0,0],"ti":[9.417,0,0]},{"i":{"x":0.833,"y":0.833},"o":{"x":0.167,"y":0.167},"t":24,"s":[60,60,0],"to":[0,0,0],"ti":[0,0,0]},{"i":{"x":0.833,"y":0.833},"o":{"x":0.167,"y":0.167},"t":36,"s":[60,60,0],"to":[-4.75,0,0],"ti":[4.75,0,0]},{"t":48,"s":[31.5,60,0]}],"ix":2},"a":{"a":1,"k":[{"i":{"x":0.667,"y":1},"o":{"x":0.167,"y":0.167},"t":18,"s":[0,0,0],"to":[0,1.5,0],"ti":[0,0,0]},{"i":{"x":0.833,"y":0.833},"o":{"x":0.333,"y":0},"t":22,"s":[0,9,0],"to":[0,0,0],"ti":[0,1.5,0]},{"t":24,"s":[0,0,0]}],"ix":1},"s":{"a":0,"k":[100,100,100],"ix":6}},"ao":0,"shapes":[{"ty":"gr","it":[{"d":1,"ty":"el","s":{"a":0,"k":[57,57],"ix":2},"p":{"a":0,"k":[0,0],"ix":3},"nm":"Ellipse Path 1","mn":"ADBE Vector Shape - Ellipse","hd":false},{"ty":"tm","s":{"a":1,"k":[{"i":{"x":[0],"y":[1]},"o":{"x":[0.167],"y":[0.167]},"t":24,"s":[49.9]},{"t":36,"s":[0]}],"ix":1},"e":{"a":1,"k":[{"i":{"x":[0.667],"y":[1]},"o":{"x":[0.167],"y":[0.167]},"t":24,"s":[50]},{"t":36,"s":[0.1]}],"ix":2},"o":{"a":0,"k":90,"ix":3},"m":1,"ix":2,"nm":"Trim Paths 1","mn":"ADBE Vector Filter - Trim","hd":false},{"ty":"st","c":{"a":0,"k":[0.070588235294,0.074509803922,0.192156862745,1],"ix":3,"x":"var $bm_rt;\n$bm_rt = thisComp.layer('Color  & Stroke Change').effect('Color 1 ')('Color');"},"o":{"a":0,"k":100,"ix":4},"w":{"a":0,"k":10,"ix":5},"lc":2,"lj":2,"bm":0,"nm":"Stroke 1","mn":"ADBE Vector Graphic - Stroke","hd":false},{"ty":"tr","p":{"a":0,"k":[0,0],"ix":2},"a":{"a":0,"k":[0,0],"ix":1},"s":{"a":0,"k":[100,100],"ix":3},"r":{"a":0,"k":0,"ix":6},"o":{"a":0,"k":100,"ix":7},"sk":{"a":0,"k":0,"ix":4},"sa":{"a":0,"k":0,"ix":5},"nm":"Transform"}],"nm":"Ellipse 1","np":3,"cix":2,"bm":0,"ix":1,"mn":"ADBE Vector Group","hd":false}],"ip":0,"op":49,"st":0,"bm":0},{"ddd":0,"ind":5,"ty":4,"nm":"Shape Layer 3","parent":2,"sr":1,"ks":{"o":{"a":0,"k":100,"ix":11},"r":{"a":0,"k":0,"ix":10},"p":{"a":1,"k":[{"i":{"x":0.833,"y":0.833},"o":{"x":0.167,"y":0.167},"t":-12,"s":[116.5,60,0],"to":[-9.417,0,0],"ti":[9.417,0,0]},{"i":{"x":0.833,"y":0.833},"o":{"x":0.167,"y":0.167},"t":12,"s":[60,60,0],"to":[0,0,0],"ti":[0,0,0]},{"i":{"x":0.833,"y":0.833},"o":{"x":0.167,"y":0.167},"t":24,"s":[60,60,0],"to":[-4.75,0,0],"ti":[9.458,0,0]},{"i":{"x":0.833,"y":0.833},"o":{"x":0.167,"y":0.167},"t":36,"s":[31.5,60,0],"to":[-9.458,0,0],"ti":[4.708,0,0]},{"t":48,"s":[3.25,60,0]}],"ix":2},"a":{"a":1,"k":[{"i":{"x":0.667,"y":1},"o":{"x":0.167,"y":0.167},"t":6,"s":[0,0,0],"to":[0,1.333,0],"ti":[0,0,0]},{"i":{"x":0.833,"y":0.833},"o":{"x":0.333,"y":0},"t":10,"s":[0,8,0],"to":[0,0,0],"ti":[0,1.333,0]},{"i":{"x":0.833,"y":0.833},"o":{"x":0.167,"y":0.167},"t":12,"s":[0,0,0],"to":[0,0,0],"ti":[0,0,0]},{"i":{"x":0.667,"y":1},"o":{"x":0.167,"y":0.167},"t":42,"s":[0,0,0],"to":[0,-1.333,0],"ti":[0,0,0]},{"i":{"x":0.833,"y":0.833},"o":{"x":0.333,"y":0},"t":46,"s":[0,-8,0],"to":[0,0,0],"ti":[0,-1.333,0]},{"t":48,"s":[0,0,0]}],"ix":1},"s":{"a":0,"k":[100,-100,100],"ix":6}},"ao":0,"shapes":[{"ty":"gr","it":[{"d":1,"ty":"el","s":{"a":0,"k":[57,57],"ix":2},"p":{"a":0,"k":[0,0],"ix":3},"nm":"Ellipse Path 1","mn":"ADBE Vector Shape - Ellipse","hd":false},{"ty":"tm","s":{"a":1,"k":[{"i":{"x":[0],"y":[1]},"o":{"x":[0.167],"y":[0.167]},"t":12,"s":[49.9]},{"t":24,"s":[0]}],"ix":1},"e":{"a":1,"k":[{"i":{"x":[0.667],"y":[1]},"o":{"x":[0.167],"y":[0.167]},"t":12,"s":[50]},{"t":24,"s":[0.1]}],"ix":2},"o":{"a":0,"k":90,"ix":3},"m":1,"ix":2,"nm":"Trim Paths 1","mn":"ADBE Vector Filter - Trim","hd":false},{"ty":"st","c":{"a":0,"k":[0.070588235294,0.074509803922,0.192156862745,1],"ix":3,"x":"var $bm_rt;\n$bm_rt = thisComp.layer('Color  & Stroke Change').effect('Color 1 ')('Color');"},"o":{"a":0,"k":100,"ix":4},"w":{"a":0,"k":10,"ix":5},"lc":2,"lj":2,"bm":0,"nm":"Stroke 1","mn":"ADBE Vector Graphic - Stroke","hd":false},{"ty":"tr","p":{"a":0,"k":[0,0],"ix":2},"a":{"a":0,"k":[0,0],"ix":1},"s":{"a":0,"k":[100,100],"ix":3},"r":{"a":0,"k":0,"ix":6},"o":{"a":0,"k":100,"ix":7},"sk":{"a":0,"k":0,"ix":4},"sa":{"a":0,"k":0,"ix":5},"nm":"Transform"}],"nm":"Ellipse 1","np":3,"cix":2,"bm":0,"ix":1,"mn":"ADBE Vector Group","hd":false}],"ip":0,"op":49,"st":-12,"bm":0},{"ddd":0,"ind":6,"ty":4,"nm":"Shape Layer 1","parent":2,"sr":1,"ks":{"o":{"a":0,"k":100,"ix":11},"r":{"a":0,"k":0,"ix":10},"p":{"a":1,"k":[{"i":{"x":0.833,"y":0.833},"o":{"x":0.167,"y":0.167},"t":-24,"s":[116.5,60,0],"to":[-9.417,0,0],"ti":[9.417,0,0]},{"i":{"x":0.833,"y":0.833},"o":{"x":0.167,"y":0.167},"t":0,"s":[60,60,0],"to":[0,0,0],"ti":[0,0,0]},{"i":{"x":0.833,"y":0.833},"o":{"x":0.167,"y":0.167},"t":12,"s":[60,60,0],"to":[-4.708,0,0],"ti":[9.417,0,0]},{"i":{"x":0.833,"y":0.833},"o":{"x":0.167,"y":0.167},"t":24,"s":[31.75,60,0],"to":[-9.417,0,0],"ti":[4.708,0,0]},{"t":36,"s":[3.5,60,0]}],"ix":2},"a":{"a":1,"k":[{"i":{"x":0.667,"y":1},"o":{"x":0.167,"y":0.167},"t":30,"s":[0,0,0],"to":[0,-1.333,0],"ti":[0,0,0]},{"i":{"x":0.833,"y":0.833},"o":{"x":0.333,"y":0},"t":34,"s":[0,-8,0],"to":[0,0,0],"ti":[0,-1.333,0]},{"t":36,"s":[0,0,0]}],"ix":1},"s":{"a":0,"k":[100,100,100],"ix":6}},"ao":0,"shapes":[{"ty":"gr","it":[{"d":1,"ty":"el","s":{"a":0,"k":[57,57],"ix":2},"p":{"a":0,"k":[0,0],"ix":3},"nm":"Ellipse Path 1","mn":"ADBE Vector Shape - Ellipse","hd":false},{"ty":"tm","s":{"a":1,"k":[{"i":{"x":[0],"y":[1]},"o":{"x":[0.167],"y":[0.167]},"t":0,"s":[49.9]},{"t":12,"s":[0]}],"ix":1},"e":{"a":1,"k":[{"i":{"x":[0.667],"y":[1]},"o":{"x":[0.167],"y":[0.167]},"t":0,"s":[50]},{"t":12,"s":[0.1]}],"ix":2},"o":{"a":0,"k":90,"ix":3},"m":1,"ix":2,"nm":"Trim Paths 1","mn":"ADBE Vector Filter - Trim","hd":false},{"ty":"st","c":{"a":0,"k":[0.070588235294,0.074509803922,0.192156862745,1],"ix":3,"x":"var $bm_rt;\n$bm_rt = thisComp.layer('Color  & Stroke Change').effect('Color 1 ')('Color');"},"o":{"a":0,"k":100,"ix":4},"w":{"a":0,"k":10,"ix":5},"lc":2,"lj":2,"bm":0,"nm":"Stroke 1","mn":"ADBE Vector Graphic - Stroke","hd":false},{"ty":"tr","p":{"a":0,"k":[0,0],"ix":2},"a":{"a":0,"k":[0,0],"ix":1},"s":{"a":0,"k":[100,100],"ix":3},"r":{"a":0,"k":0,"ix":6},"o":{"a":0,"k":100,"ix":7},"sk":{"a":0,"k":0,"ix":4},"sa":{"a":0,"k":0,"ix":5},"nm":"Transform"}],"nm":"Ellipse 1","np":3,"cix":2,"bm":0,"ix":1,"mn":"ADBE Vector Group","hd":false}],"ip":0,"op":36,"st":-24,"bm":0}],"markers":[]}